Metadata-Version: 2.1
Name: odoo-addon-l10n_be_cooperator_portal
Version: 16.0.1.0.0.13
Summary: Give access to Tax Shelter Report in the portal.
Home-page: https://github.com/OCA/cooperative
Author: Coop IT Easy SC, Odoo Community Association (OCA)
Author-email: support@odoo-community.org
License: AGPL-3
Classifier: Programming Language :: Python
Classifier: Framework :: Odoo
Classifier: Framework :: Odoo :: 16.0
Classifier: License :: OSI Approved :: GNU Affero General Public License v3
Requires-Python: >=3.10
Requires-Dist: odoo-addon-l10n-be-cooperator<16.1dev,>=16.0dev
Requires-Dist: odoo<16.1dev,>=16.0a
